[
  {
    "name": "Fire Wyvern",
    "image": "/images/wyvern.png",
    "description": "Balanced wrath of flame; excels at area damage and has fire resistance.",
    "id": "Ragnarok_Wyvern_Override_C",
    "price": "3",
    "maxLevel": false,
    "type": "Wyvern"
  },
  {
    "name": "Ice Wyvern",
    "image": "/images/wyvern.png",
    "description": "Breathes a freezing blast that slows or freezes targets; ideal for crowd control.",
    "id": "Ragnarok_Wyvern_Override_Ice_C",
    "price": "4",
    "maxLevel": false,
    "type": "Wyvern"
  },
  {
    "name": "Lightning Wyvern",
    "image": "/images/wyvern.png",
    "description": "Wyvern variant that unleashes a lightning beam whose damage scales with melee; high burst but heavy stamina drain.",
    "id": "Wyvern_Character_BP_Lightning_C",
    "price": "3",
    "maxLevel": false,
    "type": "Wyvern"
  },
  {
    "name": "Poison Wyvern",
    "image": "/images/wyvern.png",
    "description": "Shoots long-range toxic projectiles that ignore armor and deal damage over time.",
    "id": "Wyvern_Character_BP_Poison_C",
    "price": "2.5",
    "maxLevel": false,
    "type": "Wyvern"
  },
  {
    "name": "Wyvern",
    "image": "/images/wyvern.png",
    "description": "A massive dragon-like reptile with elemental breath and the ability to carry riders; must be hatched from an egg and raised.",
    "id": "Wyvern_Character_BP_Base_C",
    "price": "3",
    "maxLevel": false,
    "type": "Wyvern"
  },
  {
    "name": "Phoenix",
    "image": "/images/phoenix.png",
    "description": "A mythical bird of fire and rebirth, the Phoenix is said to burst into flames upon death, only to rise anew from its own ashes. Known for its radiant plumage, searing heat, and unmatched grace in flight, it is a symbol of immortality and renewal in countless legends.",
    "id": "Phoenix",
    "price": "5",
    "maxLevel": false,
    "type": "Fantasy Creature"
  },
  {
    "name": "Amargasaurus",
    "image": "/images/amargasaurus.png",
    "description": "Spiked sauropod with unique thermal regulation abilities.",
    "id": "Amarga_Character_BP_C",
    "price": "30",
    "maxLevel": false,
    "type": "Herbivore"
  },
  {
    "name": "Dakosaurus",
    "image": "/images/dakosaurus.png",
    "description": "Marine predator resembling a crocodile; swift underwater hunter.",
    "id": "Dakosaurus_Character_BP_C",
    "price": "4",
    "maxLevel": false,
    "type": "Aquatic"
  },
  {
    "name": "Hyaenodon",
    "image": "/images/hyaenodon.png",
    "description": "Pack-based predator that gains strength in numbers.",
    "id": "Hyaenodon_Character_BP_C",
    "price": "1",
    "maxLevel": false,
    "type": "Mammal Predator"
  },
  {
    "name": "Rhyniognatha",
    "image": "/images/rhyniognatha.png",
    "description": "Giant insect with versatile combat and utility abilities.",
    "id": "Rhynio_Character_BP_C",
    "price": "50",
    "maxLevel": false,
    "type": "Insect"
  },
  {
    "name": "Managarmr",
    "image": "/images/managarmr.png",
    "description": "Frost-breathing, agile beast capable of powerful leaps and glides.",
    "id": "Managarmr_Character_BP_C",
    "price": "15",
    "maxLevel": false,
    "type": "Fantasy Creature"
  }
]
